cdk/__init__.py
cdk/app.py
cdk/consoleme_ecs_cdk/__init__.py
cdk/consoleme_ecs_cdk/setup.py
cdk/consoleme_ecs_cdk/service/__init__.py
cdk/consoleme_ecs_cdk/service/consoleme_ecs_service_stack.py
cdk/consoleme_ecs_cdk/service/consoleme_spoke_accounts_stack.py
cdk/consoleme_ecs_cdk/service/constants.py
cdk/consoleme_ecs_cdk/service/helpers.py
cdk/consoleme_ecs_cdk/service/nested_stacks/__init__.py
cdk/consoleme_ecs_cdk/service/nested_stacks/alb_stack.py
cdk/consoleme_ecs_cdk/service/nested_stacks/auth_stack.py
cdk/consoleme_ecs_cdk/service/nested_stacks/cache_stack.py
cdk/consoleme_ecs_cdk/service/nested_stacks/compute_stack.py
cdk/consoleme_ecs_cdk/service/nested_stacks/config_stack.py
cdk/consoleme_ecs_cdk/service/nested_stacks/db_stack.py
cdk/consoleme_ecs_cdk/service/nested_stacks/domain_stack.py
cdk/consoleme_ecs_cdk/service/nested_stacks/iam_stack.py
cdk/consoleme_ecs_cdk/service/nested_stacks/shared_stack.py
cdk/consoleme_ecs_cdk/service/nested_stacks/vpc_stack.py
cdk/tests/__init__.py
cdk/tests/test_cdk.py
consoleme/__init__.py
consoleme/__main__.py
consoleme/babel.config.js
consoleme/models.py
consoleme/routes.py
consoleme/celery_tasks/__init__.py
consoleme/celery_tasks/celery_tasks.py
consoleme/config/__init__.py
consoleme/config/config.py
consoleme/default_plugins/__init__.py
consoleme/default_plugins/setup.py
consoleme/default_plugins/plugins/__init__.py
consoleme/default_plugins/plugins/auth/__init__.py
consoleme/default_plugins/plugins/auth/auth.py
consoleme/default_plugins/plugins/aws/__init__.py
consoleme/default_plugins/plugins/aws/aws.py
consoleme/default_plugins/plugins/celery_tasks/__init__.py
consoleme/default_plugins/plugins/celery_tasks/celery_tasks.py
consoleme/default_plugins/plugins/config/__init__.py
consoleme/default_plugins/plugins/config/config.py
consoleme/default_plugins/plugins/group_mapping/__init__.py
consoleme/default_plugins/plugins/group_mapping/group_mapping.py
consoleme/default_plugins/plugins/internal_routes/__init__.py
consoleme-1.4.0.dist-info/LICENSE
consoleme-1.4.0.dist-info/METADATA
consoleme-1.4.0.dist-info/WHEEL
consoleme-1.4.0.dist-info/entry_points.txt
consoleme-1.4.0.dist-info/top_level.txt
consoleme-1.4.0.dist-info/RECORD
