Metadata-Version: 2.1
Name: consoleme
Version: 1.4.0
Summary: A central control plane for AWS permissions and access
Home-page: https://github.com/Netflix/ConsoleMe
Author: Netflix Security
Author-email: consoleme-maintainers@netflix.com
License: Apache 2.0
Keywords: consoleme
Requires-Python: >=3.8
License-File: LICENSE
Requires-Dist: aiozipkin
Requires-Dist: asgiref
Requires-Dist: atlassian-python-api
Requires-Dist: bcrypt
Requires-Dist: bleach
Requires-Dist: boto3
Requires-Dist: cchardet
Requires-Dist: celery
Requires-Dist: cloudaux
Requires-Dist: cryptography
Requires-Dist: datamodel-code-generator
Requires-Dist: decorator
Requires-Dist: deepdiff
Requires-Dist: defusedxml
Requires-Dist: elasticsearch
Requires-Dist: elasticsearch-dsl
Requires-Dist: furl
Requires-Dist: gitpython
Requires-Dist: google-api-python-client
Requires-Dist: google-auth-httplib2
Requires-Dist: google-cloud-storage
Requires-Dist: gunicorn
Requires-Dist: hiredis
Requires-Dist: idna
Requires-Dist: isodate
Requires-Dist: jmespath
Requires-Dist: jsonschema
Requires-Dist: kombu
Requires-Dist: marshmallow
Requires-Dist: mccabe ==0.6.1
Requires-Dist: numpy
Requires-Dist: logmatic-python
Requires-Dist: lxml
Requires-Dist: okta-jwt
Requires-Dist: pandas
Requires-Dist: parliament
Requires-Dist: password-strength
Requires-Dist: pkgconfig
Requires-Dist: policy-sentry
Requires-Dist: policyuniverse
Requires-Dist: presto-python-client
Requires-Dist: pycurl
Requires-Dist: pydantic
Requires-Dist: pyjwt
Requires-Dist: pylint
Requires-Dist: PyNaCl
Requires-Dist: python-dateutil
Requires-Dist: python-json-logger
Requires-Dist: python3-saml
Requires-Dist: pytz
Requires-Dist: questionary
Requires-Dist: redis
Requires-Dist: requests
Requires-Dist: retry
Requires-Dist: retrying
Requires-Dist: ruamel.yaml
Requires-Dist: sentry-sdk
Requires-Dist: simplejson
Requires-Dist: six
Requires-Dist: tenacity
Requires-Dist: tornado
Requires-Dist: ujson
Requires-Dist: uvloop
Requires-Dist: validate-email
Requires-Dist: xmlsec
